{
    "cashz": [
        {
            "web": "1.0.71",
            "android": "1.0.11",
            "ios": "1.0.3"
        },
        {
            "titulo": "Atualização disponível",
            "links": [
                "android": "https://play.google.com/store/apps/details?id=com.test.cashz",
                "ios": "https://apps.apple.com/br/app/cashz/id6692627701"
            ]
        }
    ],
    "consulta_mobile": [
        {
            "web": "1.0.71",
            "android": "1.0.0",
            "ios": "1.0.0"
        },
        {
            "titulo": "Atualização disponível"
        }
    ]
}
